<?xml version="1.0" encoding="utf-8"?>
<odoo>
    <data>
        <record id="res_users_view_simple_form" model="ir.ui.view">
            <field name="name">res.users.simple.form.inherit</field>
            <field name="model">res.users</field>
            <field name="inherit_id" ref="base.view_users_simple_form"/>
            <field name="arch" type="xml">
                <xpath expr="//field[@name='mobile']" position="after">
                    <field name="po_box"/>
                </xpath>
            </field>
        </record>
    </data>
</odoo>